setup.py
AIO/AIO.py
AIO/__init__.py
AIOwiki.egg-info/PKG-INFO
AIOwiki.egg-info/SOURCES.txt
AIOwiki.egg-info/dependency_links.txt
AIOwiki.egg-info/requires.txt
AIOwiki.egg-info/top_level.txt