Metadata-Version: 1.0
Name: AIOwiki
Version: 1.1
Summary: A Python API for accessing information about episodes on AIOwiki.com
Home-page: https://github.com/themooer1/AIO
Author: David Smith
Author-email: fluffy1781@gmail.com
License: MIT
Platform: UNKNOWN
